quantumrings/__init__.py
quantumrings/toolkit/__init__.py
quantumrings/toolkit/qiskit/__init__.py
quantumrings/toolkit/qiskit/qr_backend_for_qiskit.py
quantumrings/toolkit/qiskit/qr_estimator.py
quantumrings/toolkit/qiskit/qr_job_for_qiskit.py
quantumrings/toolkit/qiskit/qr_meas.py
quantumrings/toolkit/qiskit/qr_runtime_service.py
quantumrings/toolkit/qiskit/qr_sampler.py
quantumrings/toolkit/qiskit/qr_session.py
quantumrings/toolkit/qiskit/qr_statevector.py
quantumrings/toolkit/qiskit/qr_statevector_estimator.py
quantumrings/toolkit/qiskit/qr_statevector_sampler.py
quantumrings/toolkit/qiskit/qr_translator.py
quantumrings/toolkit/qiskit/machine_learning/__init__.py
quantumrings/toolkit/qiskit/machine_learning/qr_estimator_qnn.py
quantumrings/toolkit/qiskit/machine_learning/qr_fidelity_quantum_kernel.py
quantumrings/toolkit/qiskit/machine_learning/qr_sampler_qnn.py
quantumrings/toolkit/qiskit/machine_learning/qr_trainable_fidelity_quantum_kernel.py
quantumrings_toolkit_qiskit-0.2.0.dist-info/licenses/LICENSE.rst
quantumrings_toolkit_qiskit-0.2.0.dist-info/METADATA
quantumrings_toolkit_qiskit-0.2.0.dist-info/WHEEL
quantumrings_toolkit_qiskit-0.2.0.dist-info/top_level.txt
quantumrings_toolkit_qiskit-0.2.0.dist-info/RECORD
