Metadata-Version: 2.4
Name: quantumrings-toolkit-qiskit
Version: 0.2.0
Summary: QuantumRings toolkit for Qiskit 2.x
Author-email: "Quantum Rings Inc." <contact@quantumrings.com>
License: 
Project-URL: Homepage, https://www.quantumrings.com/docs
Project-URL: Documentation, https://www.quantumrings.com/docs
Project-URL: API Reference, https://quantumrings.com/doc/modules.html
Keywords: quantum,quantum circuit,quantum computing,quantum programming language,quantum register,quantum tools,qiskit,tools,sdk
Classifier: Development Status :: 3 - Alpha
Classifier: Environment :: Console
Classifier: Intended Audience :: Developers
Classifier: Intended Audience :: Science/Research
Classifier: Topic :: Software Development :: Build Tools
Classifier: Topic :: Scientific/Engineering
Classifier: Programming Language :: Python :: 3.6
Classifier: Programming Language :: Python :: 3.7
Classifier: Programming Language :: Python :: 3.8
Classifier: Programming Language :: Python :: 3.9
Classifier: Programming Language :: Python :: 3.10
Classifier: Programming Language :: Python :: 3.11
Classifier: Programming Language :: Python :: 3.11
Classifier: Programming Language :: Python :: 3.12
Classifier: Programming Language :: Python :: 3.13
Classifier: Operating System :: Microsoft :: Windows
Classifier: Operating System :: MacOS :: MacOS X
Classifier: Operating System :: POSIX :: Linux
Requires-Python: >=3.6
License-File: LICENSE.rst
Requires-Dist: numpy
Requires-Dist: qiskit
Dynamic: license-file
